<control ref="PCI-R10-10.2.5" name="10.2.5 - Log the use of and changes to identification and authentication mechanisms-" platform="" cost="0" risk="0" state="Recommended" owner="" library="" source="MANUAL">
                    <desc>&lt;p&gt;Use of and changes to identification and authentication mechanisms-including
                        but not
                        limited to
                        creation of new accounts and elevation of privileges-and all changes, additions, or
                        deletions to
                        accounts
                        with root or administrative privileges&amp;nbsp;&lt;/p&gt;
                        &lt;p&gt; &lt;/p&gt;
                        &lt;p&gt;Without knowing who was logged on at the time of an incident, it is impossible to
                        identify the
                        accounts that may have been used. Additionally, malicious users may attempt to manipulate the
                        authentication
                        controls with the intent of bypassing them or impersonating a valid account.&amp;nbsp;&lt;/p&gt;
                    </desc>
                    <implementations/>
                    <references/>
                    <standards>
                        <standard ref="10.2.5" supportedStandardRef="PCI-DSS-v3.2"/>
                    </standards>
                    <udts/>
                    <test expiryDate="" expiryPeriod="0">
                        <steps>&lt;p&gt;10.2.5.a Verify use of identification and authentication mechanisms is logged.
                            &lt;/p&gt;
                            &lt;p&gt;10.2.5.b Verify all elevation of privileges is logged. &lt;/p&gt;
                            &lt;p&gt;10.2.5.c Verify all changes, additions, or deletions to any account with root or
                            administrative
                            privileges are logged.&amp;nbsp;&lt;/p&gt;
                        </steps>
                        <notes></notes>
                        <references/>
                        <source filename="" args="" type="Manual" result="Not Tested" enabled="true" timestamp="2016-08-05T16:53:37.567000">
                            <output></output>
                        </source>
                        <udts/>
                    </test>
                </control>