<weakness ref='AZURE-NET-04' name='Unauthorised connection attempts on Azure resources' state='0' impact='100'>
          <desc>Receiving unauthorized connections to Azure resources is most likely to be receiving an
                        attack. To avoid this, access to the network must be as restricted as possible using Network
                        Access Control Lists for blacklisting.
                    </desc>
          <test expiryDate='' expiryPeriod='0'>
            <steps>&lt;div&gt;
                            &lt;ol&gt;
                            &lt;li&gt;Log into the Azure portal as an owner.&lt;/li&gt;
                            &lt;li&gt;Select &amp;quot;Network security groups&amp;quot;.&lt;/li&gt;
                            &lt;li&gt;Select the Network Security Group (NSG) for your virtual machine and click on
                            &amp;quot;Inbound security rules&amp;quot;.&lt;/li&gt;
                            &lt;li&gt;Check that there is a rule to deny the inbound access from a blacklisted IP
                            address or range to a designated port or port range.&lt;/li&gt;
                            &lt;/ol&gt;
                            &lt;/div&gt;
                        </steps>
            <notes />
            <source filename='' args='' type='Manual' result='Not Tested' enabled='true' timestamp='2017-06-12T09:54:46.827'>
              <output></output>
            </source>
            <references />
            <udts />
          </test>
        </weakness>