<control ref="PCI-R3-3.5.1" name="3.5.1 - Maintain a documented description of the cryptographic architecture" platform="" cost="0" risk="0" state="Recommended" owner="" library="" source="MANUAL">
                    <desc>&lt;p&gt; &lt;/p&gt;The description must include:&amp;nbsp;
                        &lt;br /&gt;
                        &lt;p&gt;- Details of all algorithms, protocols, and keys used for the protection of cardholder
                        data,
                        including key strength and expiry date&amp;nbsp;&lt;/p&gt;
                        &lt;p&gt;- Description of the key usage for each key&amp;nbsp;&lt;/p&gt;
                        &lt;p&gt;- Inventory of any HSMs and other SCDs used for key management&amp;nbsp;&lt;/p&gt;
                        &lt;p&gt; &lt;/p&gt;
                        &lt;p&gt;Maintaining current documentation of the cryptographic architecture enables an entity
                        to understand
                        the algorithms, protocols, and cryptographic keys used to protect cardholder data, as well as
                        the devices
                        that generate, use and protect the keys. This allows an entity to keep pace with evolving
                        threats to their
                        architecture, enabling them to plan for updates as the assurance levels provided by different
                        algorithms/key
                        strengths changes. Maintaining such documentation also allows an entity to detect lost or
                        missing keys or
                        key-management devices, and identify unauthorized additions to their cryptographic architecture.&amp;nbsp;&lt;/p&gt;
                        &lt;p&gt;&lt;br /&gt;&lt;/p&gt;
                    </desc>
                    <implementations/>
                    <references/>
                    <standards>
                        <standard ref="3.5.1" supportedStandardRef="PCI-DSS-v3.2"/>
                    </standards>
                    <udts/>
                    <test expiryDate="" expiryPeriod="0">
                        <steps>&lt;p&gt;3.5.1 Interview responsible personnel and review documentation to verify that a
                            document
                            exists to describe the cryptographic architecture, including: &lt;/p&gt;
                            &lt;ul&gt;
                            &lt;li&gt; &lt;p&gt;Details of all algorithms, protocols, and keys used for the protection
                            of cardholder
                            data, including key strength and expiry date &lt;/p&gt; &lt;/li&gt;
                            &lt;li&gt; &lt;p&gt;Description of the key usage for each key &lt;/p&gt; &lt;/li&gt;
                            &lt;li&gt; &lt;p&gt;Inventory of any HSMs and other SCDs used for key management&amp;nbsp;&lt;/p&gt;
                            &lt;/li&gt;
                            &lt;/ul&gt;
                        </steps>
                        <notes></notes>
                        <references/>
                        <source filename="" args="" type="Manual" result="Not Tested" enabled="true" timestamp="2016-08-05T08:51:49.903000">
                            <output></output>
                        </source>
                        <udts/>
                    </test>
                </control>