<weakness ref='AWS-Monitoring-4.10' name='Changes in the security groups cannot be detected' state='0' impact='100'>
          <desc>The changes in the security groups must be audited and monitored and the correspondent
                        personnel must approve these changes. If the situation is not the correct, attackers can access
                        to security systems.
                    </desc>
          <test expiryDate='' expiryPeriod='0'>
            <steps />
            <notes />
            <source filename='' args='' type='Manual' result='Not Tested' enabled='true' timestamp='2019-04-01T07:51:15.000'>
              <output></output>
            </source>
            <references />
            <udts />
          </test>
        </weakness>