<weakness ref='GOOGLE-USECURE-CREDENTIALS' name='Credentials are not securely stored' state='0' impact='100'>
          <desc>The credentials that are used to access the resources are not securely stored and can be
                        accessed by unauthorized personnel.
                    </desc>
          <test expiryDate='' expiryPeriod='0'>
            <steps />
            <notes />
            <source filename='' args='' type='Manual' result='Not Tested' enabled='true' timestamp='2018-05-31T09:31:02.409'>
              <output></output>
            </source>
            <references />
            <udts />
          </test>
        </weakness>